python_simplex_bot/__init__.py
python_simplex_bot/bot.py
python_simplex_bot/requirements.txt
python_simplex_bot/chats/__init__.py
python_simplex_bot/groups/__init__.py
python_simplex_bot/handlers/__init__.py
python_simplex_bot/handlers/audio_handler.py
python_simplex_bot/handlers/command_handler.py
python_simplex_bot/handlers/hello_handler.py
python_simplex_bot/handlers/image_handler.py
python_simplex_bot/handlers/text_handler.py
python_simplex_bot/handlers/video_handler.py
python_simplex_bot/helpers/__init__.py
python_simplex_bot/helpers/autorun.py
python_simplex_bot/helpers/formatting.py
python_simplex_bot/helpers/limiter.py
python_simplex_bot/types/__init__.py
python_simplex_bot/types/base_context.py
python_simplex_bot/types/base_handler.py
python_simplex_bot/types/peer.py
python_simplex_bot/types/update.py
python_simplex_bot/websocket_client/__init__.py
python_simplex_bot/websocket_client/client.py
python_simplex_bot/websocket_client/commands.py
python_simplex_bot/websocket_client/datatypes.py
python_simplex_bot/websocket_client/responses.py
python_simplex_bot-0.0.1.dist-info/METADATA
python_simplex_bot-0.0.1.dist-info/WHEEL
python_simplex_bot-0.0.1.dist-info/licenses/LICENSE
python_simplex_bot-0.0.1.dist-info/RECORD
