Metadata-Version: 2.4
Name: python-simplex-bot
Version: 0.0.1
Summary: High-level Python interface for Simplex API
Project-URL: Documentation, https://github.com/maxzhiv/python-simplex-bot/blob/main/docs/README.md
Project-URL: Homepage, https://github.com/maxzhiv/python-simplex-bot
Project-URL: Issues, https://github.com/maxzhiv/python-simplex-bot/issues
Author-email: maxzhiv <mz79765@gmail.com>
License: MIT-0
License-File: LICENSE
Requires-Python: >=3.10
Requires-Dist: pydantic>=2.11.7
Requires-Dist: websockets>=15.0.1
